{
  "Жесты администратора": {
    "description": "Показывает специальные жесты для администраторов.",
    "preview": "admingestures.mp4"
  },
  "Автоприсед при беге": {
    "description": "Автоматически приседает при беге для снижения шума.",
    "preview": "autocrouch.mp4"
  },
  "Тряска от взрыва": {
    "description": "Эффект тряски экрана при взрыве рядом.",
    "preview": "bombshake.mp4"
  },
  "Ошибки в консоли": {
    "description": "Отображает ошибки и предупреждения в консоли игры.",
    "preview": "consoleerror.mp4"
  },
  "Быстрое крафтинг": {
    "description": "Ускоряет процесс создания предметов.",
    "preview": "craftfast.mp4"
  },
  "Фокус на карте": {
    "description": "Автоматически фокусируется на карте при открытии.",
    "preview": "focusmap.mp4"
  },
  "FootIK (естественная постановка ног)": {
    "description": "Корректирует положение ног персонажа на неровной поверхности.",
    "preview": "footik.mp4"
  },
  "Качание головы при ходьбе": {
    "description": "Добавляет реалистичное покачивание камеры при движении.",
    "preview": "headbob.mp4"
  },
  "Маркер попадания": {
    "description": "Визуальный и звуковой индикатор при попадании в цель.",
    "preview": "hitmarker.mp4"
  },
  "Время удержания предмета": {
    "description": "Увеличивает время, в течение которого предмет остаётся в руках после подбора.",
    "preview": "holdtime.mp4"
  },
  "Удар при повреждении": {
    "description": "Эффект удара или отдачи при получении урона.",
    "preview": "hurt punch.mp4"
  },
  "Impostor-режим": {
    "description": "Активирует визуальные эффекты, имитирующие режим 'среди нас'.",
    "preview": "impostror.mp4"
  },
  "Отключить ноги": {
    "description": "Полностью скрывает модель ног персонажа.",
    "preview": "legsoff.mp4"
  },
  "Макс. время жизни гибов": {
    "description": "Ограничивает, как долго видны частицы разрушения объектов.",
    "preview": "maxbgiblife.mp4"
  },
  "Макс. дистанция хибов": {
    "description": "Определяет, на каком расстоянии отображаются эффекты попаданий.",
    "preview": "maxhibdist.mp4"
  },
  "Контурные обводки": {
    "description": "Добавляет обводку вокруг объектов для лучшей видимости.",
    "preview": "outlines.mp4"
  },
  "Подсказки событий сервера": {
    "description": "Показывает уведомления о событиях на сервере (например, рейды).",
    "preview": "servereventtips.mp4"
  },
  "SSS-эффект": {
    "description": "Специальный визуальный эффект (например, screen space scattering).",
    "preview": "sss.mp4"
  },
  "Отключить стробоскопы": {
    "description": "Убирает мигающие световые эффекты (strobelights).",
    "preview": "strobosckope.mp4"
  },
  "Масштаб FOV оружия": {
    "description": "Регулирует поле зрения модели оружия в руках.",
    "preview": "vm_fov_scale.mp4"
  }
}